MANIFEST.in
account_voucher_data.xml
account_voucher_pay_invoice.xml
account_voucher_report.xml
account_voucher_sequence.xml
account_voucher_view.xml
account_voucher_wizard.xml
account_voucher_workflow.xml
setup.py
voucher_payment_receipt_view.xml
voucher_sales_purchase_view.xml
./__init__.py
./__openerp__.py
./account_voucher.py
./invoice.py
./report/__init__.py
./report/account_voucher.py
./report/account_voucher_print.py
./report/account_voucher_sales_receipt.py
./wizard/__init__.py
./wizard/account_statement_from_invoice.py
i18n/account_voucher.pot
i18n/ar.po
i18n/bg.po
i18n/bs.po
i18n/ca.po
i18n/cs.po
i18n/da.po
i18n/de.po
i18n/el.po
i18n/en_GB.po
i18n/es.po
i18n/es_AR.po
i18n/es_CR.po
i18n/es_EC.po
i18n/es_MX.po
i18n/es_PE.po
i18n/es_PY.po
i18n/es_VE.po
i18n/et.po
i18n/fa.po
i18n/fi.po
i18n/fr.po
i18n/gl.po
i18n/gu.po
i18n/hi.po
i18n/hr.po
i18n/hu.po
i18n/id.po
i18n/it.po
i18n/ja.po
i18n/ko.po
i18n/lt.po
i18n/mk.po
i18n/mn.po
i18n/nb.po
i18n/nl.po
i18n/nl_BE.po
i18n/oc.po
i18n/pl.po
i18n/pt.po
i18n/pt_BR.po
i18n/ro.po
i18n/ru.po
i18n/sl.po
i18n/sq.po
i18n/sr.po
i18n/sr@latin.po
i18n/sv.po
i18n/tlh.po
i18n/tr.po
i18n/uk.po
i18n/vi.po
i18n/zh_CN.po
i18n/zh_TW.po
images/customer_invoice.jpeg
images/customer_payment.jpeg
images/customer_refunds.jpeg
images/journal_voucher.jpeg
images/sales_receipt.jpeg
images/supplier_voucher.jpeg
openerp_account_voucher.egg-info/PKG-INFO
openerp_account_voucher.egg-info/SOURCES.txt
openerp_account_voucher.egg-info/dependency_links.txt
openerp_account_voucher.egg-info/requires.txt
openerp_account_voucher.egg-info/top_level.txt
report/account_voucher.rml
report/account_voucher.sxw
report/account_voucher_print.rml
report/account_voucher_print.sxw
report/account_voucher_sales_receipt_view.xml
security/account_voucher_security.xml
security/ir.model.access.csv
static/src/img/icon.png
test/account_voucher.yml
test/account_voucher_report.yml
test/case1_usd_usd.yml
test/case1_usd_usd_payment_rate.yml
test/case2_suppl_usd_eur.yml
test/case2_usd_eur_debtor_in_eur.yml
test/case2_usd_eur_debtor_in_usd.yml
test/case3_eur_eur.yml
test/case4_cad_chf.yml
test/case5_suppl_usd_usd.yml
test/case_eur_usd.yml
test/sales_payment.yml
test/sales_receipt.yml
